Metadata-Version: 1.0
Name: seg-models-dangat
Version: 1.1
Summary: To Compare Segmentation Models for satellite imagery
Home-page: UNKNOWN
Author: Daniel Gaitan Forero
Author-email: danielgaitanforero@gmail.com
License: MIT
Platform: UNKNOWN
